{
    "name":"table",
    "content":"tr_content",
    "uuid":"hp_query_emp",
    "dataUrl":"hp_query_emp?dbs=hp&showColumn=1",
    "templet":"default_table.html",
    "displayquery":"inline-block",
    "displayimport":"none",
    "displayexport":"none",
    "child":[       
        {
            "th_content":"id",
            "width":"5%",
            "templet":"default_table_th.html"
        },
        {
            "th_content":"ehrno",
            "width":"3%",
            "templet":"default_table_th.html"
        },        
        {
            "th_content":"姓名",
            "width":"5%",
            "templet":"default_table_th.html"
        },
        {
            "th_content":"工号",
            "width":"5%",
            "templet":"default_table_th.html"
        },        
        {
            "th_content":"邮箱",
            "width":"12%",
            "templet":"default_table_th.html"
        },
        {
            "th_content":"手机号",
            "width":"5%",
            "templet":"default_table_th.html"
        },
        {
            "th_content":"岗位",
            "width":"8%",
            "templet":"default_table_th.html"
        },
        {
            "th_content":"入职时间",
            "width":"6%",
            "templet":"default_table_th.html"
        },
        {
            "th_content":"生日",
            "width":"6%",
            "templet":"default_table_th.html"
        },
        {
            "th_content":"部门",
            "width":"10%",
            "templet":"default_table_th.html"
        }
    ]
}
